{
  "id": "perplexitybot",
  "name": "PerplexityBot",
  "vendor": "Perplexity",
  "userAgent": "Mozilla/5.0 AppleWebKit/537.36 (KHTML, like Gecko; compatible; PerplexityBot/1.0; +https://perplexity.ai/perplexitybot)",
  "robotsTxtToken": "PerplexityBot",
  "purpose": "search-indexing",
  "rendersJavaScript": false,
  "respectsRobotsTxt": true,
  "crawlDelaySupported": "unknown",
  "ipRangesUrl": "https://www.perplexity.com/perplexitybot.json",
  "docs": "https://docs.perplexity.ai/docs/resources/perplexity-crawlers",
  "confidence": {
    "rendersJavaScript": {
      "value": false,
      "level": "observed",
      "source": "Most third-party reports indicate no JS rendering"
    },
    "respectsRobotsTxt": {
      "value": true,
      "level": "official",
      "source": "https://docs.perplexity.ai/docs/resources/perplexity-crawlers"
    }
  },
  "lastVerified": "2026-04-11",
  "relatedBots": ["perplexity-user"],
  "notes": "Designed to surface and link websites in search results on Perplexity. NOT used to crawl content for AI foundation models. Changes may take up to 24 hours to reflect."
}
